Metadata-Version: 1.0
Name: do-not-touch-it
Version: 1.0
Summary: simple and reliable way to make immutable classes in python
Home-page: UNKNOWN
Author: UNKNOWN
Author-email: timur20041229@gmail.com
License: UNKNOWN
Platform: UNKNOWN
